{
  "description": "Mitsuha dan Taki secara misterius saling bertukar tubuh, membuat mereka harus menjalani kehidupan satu sama lain. Dalam prosesnya, tumbuh perasaan di antara keduanya meski dipisahkan oleh waktu dan takdir.",
  "video": "vidio.html#dr-stone-ryuusui",
  "production": "TMS Entertainment",
  "release": "10 Juli 2022",
  "rating": "8.1",
  "episodes": [
    {
      "number": 1,
      "url": "https://yoru.my.id/kdrive/00CZnPaZ8q5/Kuramanime-DRSTN_MOV_BD-720p-KuramaBD.mp4?lud=1743502630&pid=7649&sid=38813&cce=1"
    }
  ]
}
