{
  "title": "Eiga Daisuki Pompo-san",
  "altTitle": "映画大好きポンポさん",
  "cover": "https://cdn.myanimelist.net/r/200x268/images/anime/1654/106235.webp",
  "genre": ["Comedy", "Drama"],
  "description": "Joelle Davidovich Pomponette, lebih dikenal sebagai Pompo, adalah produser film yang sangat berbakat, mewarisi koneksi dan mata sinematik kakeknya. Terlepas dari pandangannya yang menjanjikan, Pompo menolak untuk memproduksi apa pun selain film-B yang tidak bermutu. Begitulah, sampai dia menyerahkan asistennya, Gene Fini, sebuah naskah untuk skenario ambisius tentang kehidupan seorang komposer dan mengumumkan bahwa dia telah mendapatkan kredit penyutradaraan pertamanya.",
  "video": "vidio.html#eiga-daisuki-pompo-san",
  "production": "CLAP",
  "release": "4 Juni 2021",
  "rating": "8.1",
  "episodes": [
    {
      "number": 1,
      "url": "https://juliet.my.id/kdrive/ykBZGBjNPl5/Kuramanime-PMPCINE_MOV_BD-720p-EmotPekmen.mp4?lud=1743503067&pid=1644&sid=66011&cce="
    }
  ]
}
