{
  "title": "Kakuriyo no Yadomeshi Ni",
  "altTitle": "Kakuriyo: Bed & Breakfast for Spirits Season 2",
  "cover": "https://cdn.myanimelist.net/images/anime/1619/151364l.jpg",
  "genre": ["Fantasy", "Romance", "Gourmet"],
  "description": "Musim kedua dari kisah Kakuriyo no Yadomeshi yang berjudul “Ni”, menceritakan kembali perjalanan Aoi Tsubaki di dunia roh untuk menebus hutang keluarganya lewat membuka restoran bersama sang dewa penginapan Odanna. Musim ini diproduksi oleh GONZO bersama Makaria, dan dijadwalkan tayang mulai Oktober 2025. 5",
  "video": "vidio.html#kakuriyo-no-yadomeshi-ni",
  "production": "GONZO × Makaria",
  "release": "1 Oktober 2025",
  "rating": "",
  "episodes": [
    {
      "number": 1,
      "url": "https://chinatsu.my.id/kdrive/kMg3NeLjVzou/Kuramanime-KAKURYO_S2-01-720p.mp4?lud=1759342074&pid=37607&sid=196563&cce=1"
    },
    {
      "number": 2,
      "url": "https://celestia.my.id/kdrive/iY2xhkR1UkoT/Kuramanime-KAKURYO_S2-02-720p.mp4?lud=1759940091&pid=38219&sid=199288&cce=1"
    },
    {
      "number": 3,
      "url": "https://juliet.my.id/kdrive/iMFerzfupfGF/Kuramanime-KAKURYO_S2-03-720p.mp4?lud=1760544269&pid=38677&sid=201824&cce=1"
    },
    {
      "number": 4,
      "url": "https://kanade.my.id/kdrive/X8T3uJSiqjSxlZT/Kuramanime-KAKURYO_S2-04-720p.mp4?lud=1761149220&pid=38980&sid=203316&cce=1"
    },
    {
      "number": 5,
      "url": "https://yae.my.id/kdrive/mYFjGS318W0am7/Kuramanime-KAKURYO_S2-05-720p.mp4?lud=1761754212&pid=39319&sid=204994&cce=1"
    }
  ]
}
